alkana/__init__.py
alkana/console.py
alkana/data.py
alkana/main.py
alkana.py-0.0.1.dist-info/LICENSE
alkana.py-0.0.1.dist-info/METADATA
alkana.py-0.0.1.dist-info/WHEEL
alkana.py-0.0.1.dist-info/entry_points.txt
alkana.py-0.0.1.dist-info/top_level.txt
alkana.py-0.0.1.dist-info/RECORD
