Metadata-Version: 2.1
Name: alkana.py
Version: 0.0.1
Summary: A tool to get the katakana reading of an alphabetical string.
Home-page: https://github.com/cod-sushi/alkana.py
Author: cod
Author-email: cod.sushi@gmail.jp
License: GPLv2
Platform: UNKNOWN
Classifier: Development Status :: 3 - Alpha
Classifier: Programming Language :: Python :: 3.6
Classifier: Natural Language :: Japanese
Classifier: License :: OSI Approved :: GNU General Public License v2 (GPLv2)
Requires-Python: >=3.0, <4.0
